codeship_yaml/__init__.py
codeship_yaml/main.py
codeship_yaml-0.4.0.dist-info/LICENSE
codeship_yaml-0.4.0.dist-info/METADATA
codeship_yaml-0.4.0.dist-info/WHEEL
codeship_yaml-0.4.0.dist-info/entry_points.txt
codeship_yaml-0.4.0.dist-info/top_level.txt
codeship_yaml-0.4.0.dist-info/RECORD
