Metadata-Version: 2.1
Name: codeship-yaml
Version: 0.4.0
Summary: YAML configuration file support for Codeship.
Home-page: https://github.com/painless-software/codeship-yaml
Author: Peter Bittner
Author-email: peter@painless.software
Maintainer: Painless Software
Maintainer-email: info@painless.software
License: GPLv3
Keywords: build server,continuous integration,continuous delivery,devops,infrastructure,tools
Platform: UNKNOWN
Classifier: Development Status :: 4 - Beta
Classifier: Environment :: Console
Classifier: Intended Audience :: Developers
Classifier: License :: OSI Approved :: GNU General Public License v3 (GPLv3)
Classifier: Operating System :: OS Independent
Classifier: Programming Language :: Python
Classifier: Programming Language :: Python :: 2
Classifier: Programming Language :: Python :: 2.7
Classifier: Programming Language :: Python :: 3
Classifier: Programming Language :: Python :: 3.4
Classifier: Programming Language :: Python :: 3.5
Classifier: Programming Language :: Python :: 3.6
Classifier: Programming Language :: Python :: 3.7
Classifier: Topic :: Software Development :: Build Tools
Requires-Dist: PyYAML
